tangerine_auth/__init__.py
tangerine_auth/__version__.py
tangerine_auth/key_lime.py
tangerine_auth/yuzu.py
tangerine_auth-0.0.75.dist-info/LICENSE
tangerine_auth-0.0.75.dist-info/METADATA
tangerine_auth-0.0.75.dist-info/WHEEL
tangerine_auth-0.0.75.dist-info/entry_points.txt
tangerine_auth-0.0.75.dist-info/top_level.txt
tangerine_auth-0.0.75.dist-info/RECORD
