Metadata-Version: 2.1
Name: tangerine-auth
Version: 0.0.75
Summary: Tangerine Auth: An easy to use authentication manager for Tangerine and Flask.
Home-page: https://github.com/noraa-july-stoke/yuzu
Author: Noraa Stoke
Author-email: noraa.july.stoke@gmail.com
License: MIT
Keywords: package development template
Classifier: Development Status :: 4 - Beta
Classifier: Intended Audience :: Developers
Classifier: Programming Language :: Python :: 3.9
Requires-Python: >=3.7
License-File: LICENSE
Requires-Dist: pyjwt
Requires-Dist: bcrypt
Requires-Dist: cryptography
